pygix/__init__.py
pygix/_version.py
pygix/grazing_geometry.py
pygix/grazing_units.py
pygix/io.py
pygix/lattice.py
pygix/plotting.py
pygix/process.py
pygix/tools.py
pygix/transform.py
pygix-2022.11.14.dist-info/LICENSE
pygix-2022.11.14.dist-info/METADATA
pygix-2022.11.14.dist-info/WHEEL
pygix-2022.11.14.dist-info/top_level.txt
pygix-2022.11.14.dist-info/RECORD
